tcatlib/__init__.py
tcatlib/parsers.py
tcatlib/printing.py
tcatlib/scripts/__init__.py
tcatlib/scripts/tcat.py
tcatlib-1.0.1.dist-info/METADATA
tcatlib-1.0.1.dist-info/WHEEL
tcatlib-1.0.1.dist-info/entry_points.txt
tcatlib-1.0.1.dist-info/top_level.txt
tcatlib-1.0.1.dist-info/RECORD
