Metadata-Version: 2.1
Name: tcatlib
Version: 1.0.1
Summary: tcat utility
Author-email: James Mathews <mathewj2@mskcc.org>
Project-URL: Documentation, https://github.com/jimmymathews/tcat
Requires-Python: >=3.10
Requires-Dist: tabulate ==0.8.10
Requires-Dist: pandas ==2.0.2
